heatdesalination/__init__.py
heatdesalination/__main__.py
heatdesalination/__utils__.py
heatdesalination/argparser.py
heatdesalination/assessor.py
heatdesalination/fileparser.py
heatdesalination/heat_pump.py
heatdesalination/hpc_launch_script.py
heatdesalination/hpc_wrapper.py
heatdesalination/matrix.py
heatdesalination/optimiser.py
heatdesalination/parallel_optimiser.py
heatdesalination/parallel_simulator.py
heatdesalination/plant.py
heatdesalination/simulator.py
heatdesalination/solar.py
heatdesalination/water_pump.py
heatdesalination/weather.py
heatdesalination/storage/__init__.py
heatdesalination/storage/storage_utils.py
heatdesalination/tests/__init__.py
heatdesalination/tests/mut/__init__.py
heatdesalination/tests/mut/test_matrix.py
heatdesalination/tests/mut/test_optimiser.py
heatdesalination/tests/mut/test_simulator.py
heatdesalination/tests/mut/test_solar.py
heat_desalination-1.0.0a3.dist-info/LICENSE
heat_desalination-1.0.0a3.dist-info/METADATA
heat_desalination-1.0.0a3.dist-info/NOTICE.md
heat_desalination-1.0.0a3.dist-info/WHEEL
heat_desalination-1.0.0a3.dist-info/entry_points.txt
heat_desalination-1.0.0a3.dist-info/top_level.txt
heat_desalination-1.0.0a3.dist-info/RECORD
