Metadata-Version: 2.1
Name: heat-desalination
Version: 1.0.0a3
Summary: Hybrid Electric And Thermal Desalination
Home-page: https://github.com/BenWinchester/HEATDesalination
Author: Ben Winchester,Jenny Nelson, Christos N. Markides
Author-email: benedict.winchester@gmail.com,jenny.nelson@imperial.ac.uk,c.markides@imperial.ac.uk
Project-URL: Bug Tracker, https://github.com/BenWinchester/HEATDesalination/issues
Classifier: Programming Language :: Python :: 3.10
Classifier: License :: OSI Approved :: MIT License
Classifier: Operating System :: OS Independent
Requires-Python: >=3.10
License-File: LICENSE
License-File: NOTICE.md
Requires-Dist: numpy (>=1.23.4)
Requires-Dist: pandas (>=1.5.1)
Requires-Dist: PyYAML (>=6.0)
Requires-Dist: requests (>=2.28.1)
Requires-Dist: scipy (>=1.9.3)
Requires-Dist: seaborn (>=0.12.1)
Requires-Dist: tqdm (>=4.64.1)
